onnx_clip/__init__.py
onnx_clip/data/.gitattributes
onnx_clip/data/CLIP.png
onnx_clip/data/bpe_simple_vocab_16e6.txt.gz
onnx_clip/data/expected_preprocessed_image.npy
onnx_clip/data/franz-kafka.jpg
onnx_clip/model.py
onnx_clip/preprocessor.py
onnx_clip/tokenizer.py
onnx_clip-4.0.0.dist-info/LICENSE
onnx_clip-4.0.0.dist-info/METADATA
onnx_clip-4.0.0.dist-info/WHEEL
onnx_clip-4.0.0.dist-info/RECORD
