Metadata-Version: 2.1
Name: onnx-clip
Version: 4.0.0
Summary: CLIP with ONNX Runtime and without PyTorch dependencies.
Author: Lakera AI
Author-email: dev@lakera.ai
Requires-Python: >=3.8,<4.0
Classifier: License :: OSI Approved :: MIT License
Classifier: Operating System :: OS Independent
Classifier: Programming Language :: Python :: 3
Classifier: Programming Language :: Python :: 3.8
Classifier: Programming Language :: Python :: 3.9
Classifier: Programming Language :: Python :: 3.10
Classifier: Programming Language :: Python :: 3.11
Requires-Dist: ftfy (>=6.0.3,<7.0.0)
Requires-Dist: numpy (>=1.18.0,<2.0.0)
Requires-Dist: onnxruntime (>=1.4.0)
Requires-Dist: opencv-python-headless (>=4.0.1,<5.0.0)
Requires-Dist: pillow (>=10.1.0,<11.0.0)
Requires-Dist: regex
Requires-Dist: requests (>=2.26.0,<3.0.0)
